{"mean":{"confidence_interval":{"confidence_level":0.95,"lower_bound":3500099.1225990555,"upper_bound":3509487.946856797},"point_estimate":3504122.734585097,"standard_error":2421.0871866844923},"median":{"confidence_interval":{"confidence_level":0.95,"lower_bound":3499581.1147540985,"upper_bound":3502701.8388636364},"point_estimate":3501812.501888736,"standard_error":871.0051851592734},"median_abs_dev":{"confidence_interval":{"confidence_level":0.95,"lower_bound":4944.441582556577,"upper_bound":7454.415644569692},"point_estimate":6246.828256593057,"standard_error":628.0278337221848},"slope":{"confidence_interval":{"confidence_level":0.95,"lower_bound":3496246.316400178,"upper_bound":3501690.96380277},"point_estimate":3498996.349932023,"standard_error":1395.936799664986},"std_dev":{"confidence_interval":{"confidence_level":0.95,"lower_bound":8172.002028511639,"upper_bound":37526.306993301114},"point_estimate":24247.44281647055,"standard_error":7742.393941004819}}