{"mean":{"confidence_interval":{"confidence_level":0.95,"lower_bound":63404154.167624995,"upper_bound":63424663.3079375},"point_estimate":63414392.0325,"standard_error":5235.825244552665},"median":{"confidence_interval":{"confidence_level":0.95,"lower_bound":63399275.75,"upper_bound":63423527.5},"point_estimate":63407755.5,"standard_error":5486.786023707177},"median_abs_dev":{"confidence_interval":{"confidence_level":0.95,"lower_bound":37983.09937566519,"upper_bound":60517.8776755929},"point_estimate":48227.49454379082,"standard_error":5783.526550443764},"slope":null,"std_dev":{"confidence_interval":{"confidence_level":0.95,"lower_bound":44664.6742763042,"upper_bound":60110.793028298525},"point_estimate":52760.5049409433,"standard_error":3947.6095919553777}}